pytest_dynamicrerun
