Metadata-Version: 1.2
Name: pytest-dynamicrerun
Version: 1.1.1
Summary: A pytest plugin to rerun tests dynamically based off of test outcome and output.
Home-page: https://github.com/gnikonorov/pytest-dynamicrerun
Author: Gleb Nikonorov
Author-email: gleb.i.nikonorov@gmail.com
Maintainer: Gleb Nikonorov
Maintainer-email: gleb.i.nikonorov@gmail.com
License: MIT
Platform: UNKNOWN
Classifier: Development Status :: 4 - Beta
Classifier: Framework :: Pytest
Classifier: Intended Audience :: Developers
Classifier: Topic :: Software Development :: Testing
Classifier: Programming Language :: Python
Classifier: Programming Language :: Python :: 3.5
Classifier: Programming Language :: Python :: 3.6
Classifier: Programming Language :: Python :: 3.7
Classifier: Programming Language :: Python :: 3.8
Classifier: Programming Language :: Python :: Implementation :: PyPy
Classifier: Operating System :: OS Independent
Classifier: License :: OSI Approved :: MIT License
Requires-Python: >=3.5
